testpypibkonon/__init__.py
testpypibkonon/m_mod_bkonon.py
testpypibkonon-0.0.1.dist-info/LICENSE.txt
testpypibkonon-0.0.1.dist-info/METADATA
testpypibkonon-0.0.1.dist-info/WHEEL
testpypibkonon-0.0.1.dist-info/top_level.txt
testpypibkonon-0.0.1.dist-info/RECORD
