Metadata-Version: 2.1
Name: testpypibkonon
Version: 0.0.1
Summary: My test package
Author-email: bkonon <b327konon@gmail.com>
License: MIT License
Keywords: testpypibkonon,name,surname
Classifier: Programming Language :: Python :: 3.12
Requires-Python: >=3.0
License-File: LICENSE.txt
Requires-Dist: numpy
